codeinclude/__init__.py
codeinclude/languages.py
codeinclude/plugin.py
codeinclude/resolver.py
mkdocs_codeinclude_plugin-0.2.1.dist-info/LICENSE
mkdocs_codeinclude_plugin-0.2.1.dist-info/METADATA
mkdocs_codeinclude_plugin-0.2.1.dist-info/WHEEL
mkdocs_codeinclude_plugin-0.2.1.dist-info/entry_points.txt
mkdocs_codeinclude_plugin-0.2.1.dist-info/top_level.txt
mkdocs_codeinclude_plugin-0.2.1.dist-info/RECORD
