Metadata-Version: 2.1
Name: mkdocs-codeinclude-plugin
Version: 0.2.1
Summary: A plugin to include code snippets into mkdocs pages
Home-page: https://github.com/rnorth/mkdocs-codeinclude-plugin
Author: Richard North
Author-email: rich.north@gmail.com
License: MIT
Keywords: mkdocs python markdown codeinclude
Platform: UNKNOWN
Classifier: Intended Audience :: Developers
Classifier: Intended Audience :: Information Technology
Classifier: License :: OSI Approved :: MIT License
Classifier: Programming Language :: Python
Classifier: Programming Language :: Python :: 3 :: Only
Classifier: Programming Language :: Python :: 3.6
Requires-Python: >=3.7
Requires-Dist: mkdocs (>=1.2)
Requires-Dist: pygments (>=2.9.0)
